rearrange_pdf/__init__.py
rearrange_pdf/cli.py
rearrange_pdf/core.py
rearrange_pdf-0.1.2.dist-info/licenses/LICENSE
rearrange_pdf-0.1.2.dist-info/METADATA
rearrange_pdf-0.1.2.dist-info/WHEEL
rearrange_pdf-0.1.2.dist-info/entry_points.txt
rearrange_pdf-0.1.2.dist-info/top_level.txt
rearrange_pdf-0.1.2.dist-info/RECORD
