Metadata-Version: 2.4
Name: rearrange-pdf
Version: 0.1.2
Summary: A tool to rearrange PDF pages for printing booklets
Home-page: https://github.com/htlin222/rearrange-pdf.git
Author: htlin
Author-email: your.email@example.com
Classifier: Programming Language :: Python :: 3
Classifier: License :: OSI Approved :: MIT License
Classifier: Operating System :: OS Independent
Requires-Python: >=3.6
License-File: LICENSE
Requires-Dist: PyPDF2>=2.0.0
Dynamic: author
Dynamic: author-email
Dynamic: classifier
Dynamic: description
Dynamic: description-content-type
Dynamic: home-page
Dynamic: license-file
Dynamic: requires-dist
Dynamic: requires-python
Dynamic: summary
